Workbook

Sheet Raw_Data
A1: Product | B1: Base_Price | C1: Expected_Volume
A2: Shampoo | B2: 120 | C2: 10000
A3: Soap | B3: 40 | C3: 25000
A4: Toothpaste | B4: 90 | C4: 15000

Sheet Cost_Structure
A1: Product | B1: Variable_Cost | C1: Fixed_Cost
A2: Shampoo | B2: 70 | C2: 200000
A3: Soap | B3: 22 | C3: 120000
A4: Toothpaste | B4: 55 | C4: 150000

Sheet Pricing_Model
A1: Product | B1: Price | C1: Volume | D1: Revenue | E1: Variable Cost | F1: Gross Profit | G1: Margin %
A2: =Raw_Data!A2 -> Shampoo | B2: =Raw_Data!B2 -> 120 | C2: =Raw_Data!C2 -> 10000 | D2: =B2*C2 -> 1200000 | E2: =_xlfn.XLOOKUP(A2,Cost_Structure!A:A,Cost_Structure!B:B)*C2 -> 700000 | F2: =D2-E2 -> 500000 | G2: =F2/D2 -> 0.41666667
A3: =Raw_Data!A3 -> Soap | B3: =Raw_Data!B3 -> 40 | C3: =Raw_Data!C3 -> 25000 | D3: =B3*C3 -> 1000000 | E3: =_xlfn.XLOOKUP(A3,Cost_Structure!A:A,Cost_Structure!B:B)*C3 -> 550000 | F3: =D3-E3 -> 450000 | G3: =F3/D3 -> 0.45
A4: =Raw_Data!A4 -> Toothpaste | B4: =Raw_Data!B4 -> 90 | C4: =Raw_Data!C4 -> 15000 | D4: =B4*C4 -> 1350000 | E4: =_xlfn.XLOOKUP(A4,Cost_Structure!A:A,Cost_Structure!B:B)*C4 -> 825000 | F4: =D4-E4 -> 525000 | G4: =F4/D4 -> 0.38888889

Sheet Scenario_Analysis
A1: Scenario | B1: Price_Change | C1: Volume_Change | D1: Impact_On_Profit
A2: Discount | B2: -0.1 | C2: 0.15 | D2: Price ↓ increases volume but reduces margin
A3: Base | B3: 0 | C3: 0 | D3: Current pricing strategy
A4: Premium | B4: 0.1 | C4: -0.05 | D4: Higher margin, lower volume

Sheet Insights
A1: Key Business Insights
A3: • Shampoo generates highest absolute profit
A4: • Discounts improve volume but hurt margins
A5: • Premium pricing improves margins but risks volume loss
