Workbook

Sheet Raw_Customer_Data
A1: Customer_ID | B1: Avg_Order_Value | C1: Purchase_Frequency | D1: Retention_Rate | E1: Acquisition_Cost
A2: C001 | B2: 1200 | C2: 6 | D2: 0.65 | E2: 1500
A3: C002 | B3: 800 | C3: 4 | D3: 0.55 | E3: 1200
A4: C003 | B4: 1500 | C4: 8 | D4: 0.75 | E4: 2000
A5: C004 | B5: 600 | C5: 3 | D5: 0.45 | E5: 900

Sheet CLV_Metrics
A1: Metric | B1: Value
A2: Discount_Rate | B2: 0.1
A3: Time_Horizon_Years | B3: 5

Sheet CLV_Model
A1: Customer_ID | B1: Annual_Revenue | C1: Gross_CLV | D1: Net_CLV
A2: =Raw_Customer_Data!A2 -> C001 | B2: =Raw_Customer_Data!B2*Raw_Customer_Data!C2 -> 7200 | C2: =B2*Raw_Customer_Data!D2*(1-(1+CLV_Metrics!B2)^-CLV_Metrics!B3)/CLV_Metrics!B2 -> 17740.882 | D2: =C2-Raw_Customer_Data!E2 -> 16240.882
A3: =Raw_Customer_Data!A3 -> C002 | B3: =Raw_Customer_Data!B3*Raw_Customer_Data!C3 -> 3200 | C3: =B3*Raw_Customer_Data!D3*(1-(1+CLV_Metrics!B2)^-CLV_Metrics!B3)/CLV_Metrics!B2 -> 6671.7847 | D3: =C3-Raw_Customer_Data!E3 -> 5471.7847
A4: =Raw_Customer_Data!A4 -> C003 | B4: =Raw_Customer_Data!B4*Raw_Customer_Data!C4 -> 12000 | C4: =B4*Raw_Customer_Data!D4*(1-(1+CLV_Metrics!B2)^-CLV_Metrics!B3)/CLV_Metrics!B2 -> 34117.081 | D4: =C4-Raw_Customer_Data!E4 -> 32117.081
A5: =Raw_Customer_Data!A5 -> C004 | B5: =Raw_Customer_Data!B5*Raw_Customer_Data!C5 -> 1800 | C5: =B5*Raw_Customer_Data!D5*(1-(1+CLV_Metrics!B2)^-CLV_Metrics!B3)/CLV_Metrics!B2 -> 3070.5373 | D5: =C5-Raw_Customer_Data!E5 -> 2170.5373

Sheet Segmentation
A1: Customer_ID | B1: Net_CLV | C1: Segment
A2: =CLV_Model!A2 -> C001 | B2: =CLV_Model!D2 -> 16240.882 | C2: =IF(B2>5000,"High Value",IF(B2>2500,"Medium Value","Low Value")) -> High Value
A3: =CLV_Model!A3 -> C002 | B3: =CLV_Model!D3 -> 5471.7847 | C3: =IF(B3>5000,"High Value",IF(B3>2500,"Medium Value","Low Value")) -> High Value
A4: =CLV_Model!A4 -> C003 | B4: =CLV_Model!D4 -> 32117.081 | C4: =IF(B4>5000,"High Value",IF(B4>2500,"Medium Value","Low Value")) -> High Value
A5: =CLV_Model!A5 -> C004 | B5: =CLV_Model!D5 -> 2170.5373 | C5: =IF(B5>5000,"High Value",IF(B5>2500,"Medium Value","Low Value")) -> Low Value

Sheet Insights
A1: Key Business Insights
A3: • High-value customers generate significantly higher lifetime profit
A4: • Retention rate has a stronger impact on CLV than acquisition cost
A5: • Low CLV customers require cost-effective engagement strategies
